spkdevtools/__init__.py
spkdevtools/s3_utils.py
spkdevtools/sso_utils.py
spkdevtools-0.1.0.dist-info/METADATA
spkdevtools-0.1.0.dist-info/WHEEL
spkdevtools-0.1.0.dist-info/entry_points.txt
spkdevtools-0.1.0.dist-info/top_level.txt
spkdevtools-0.1.0.dist-info/RECORD
